Workbook

Sheet Instrucciones
B2: Sistema de Gestión Financiera — Empresa Importadora de Señuelos
B3: Plantilla base sin costo de software. Diseñada para escalar a un ERP o base de datos en el futuro.
B5: 1. Convención de IDs
B6: Cada fila de Pagos_Aportes, Costos_Compras y Ventas_Ingresos tiene un ID único (ID0001, ID0002...). Ese mismo ID va como prefijo del nombre del archivo del comprobante en Drive/Dropbox. Ej: fila ID0007 -> archivo '2026-08-27_ID0007_transferencia_socio1.pdf'.
B8: 2. Dónde van los archivos
B9: Los comprobantes (fotos, PDF) NO se pegan en el Excel. Se guardan en una carpeta de Drive/Dropbox organizada por año/mes. En la columna 'Comprobante (archivo)' se escribe el nombre del archivo (o se pega el link de Drive si lo comparten).
B11: 3. Celdas amarillas
B12: Son las únicas celdas donde deben escribir datos manualmente. El resto son fórmulas: no las sobrescriban o se rompen los cálculos.
B14: 4. Texto azul
B15: Son valores de referencia/configuración (ej: % de reparto 65/35, cotización del dólar). Se editan en la hoja Resumen_Socios.
B17: 5. Pagos_Aportes
B18: Cargar TODO lo que sale de la empresa: pagos al proveedor de China, gastos operativos, impuestos, comisiones, etc. La planilla calcula automáticamente cuánto le correspondía aportar a cada socio (65/35) vs. cuánto aportó realmente, y arrastra el saldo entre ambos.
... B30: Cada hoja está pensada como una tabla de base de datos (una fila = un registro, con ID único). El día que quieran pasar a Google Sheets + Apps Script, Airtable, o un ERP (Tango, Xubio, Contabilium), estas mismas columnas se importan directo sin rehacer la estructura.

Sheet Pagos_Aportes
A1: PAGOS Y APORTES — Todo lo que sale de la empresa
A2: Cargar cada pago realizado. Las columnas J a M se calculan solas según el % de reparto definido en Resumen_Socios.
A4: ID | B4: Fecha | C4: Descripción / Concepto | D4: Categoría | E4: Moneda origen | F4: Monto original | G4: Cotización usada (ARS) | H4: Monto Total (ARS) | I4: Pagó (Socio1/Socio2) | J4: Corresponde Socio1 (ARS) | K4: Corresponde Socio2 (ARS) | L4: Aportó Socio1 (ARS) | M4: Aportó Socio2 (ARS) | N4: Comprobante (archivo/link) | O4: Estado | P4: Notas
A5: =IF(C5="","","ID"&TEXT(ROW()-4,"0000")) -> ID0001 | B5: 2026-08-27 | C5: Pago factura proveedor China - Pedido #45 | D5: Importación | E5: USD | F5: 1000 | G5: 1300 | H5: =F5*G5 -> 1300000 | I5: Socio1 | J5: =$H5*Resumen_Socios!$D$5 -> 845000 | K5: =$H5*Resumen_Socios!$D$6 -> 455000 | L5: =IF(I5="Socio1",H5,0) -> 1300000 | M5: =IF(I5="Socio2",H5,0) -> 0 | N5: 2026-08-27_ID0001_transferencia_proveedorChina.pdf | O5: Pagado | P5: Anticipo pedido señuelos
A6: =IF(C6="","","ID"&TEXT(ROW()-4,"0000")) | H6: =IF(C6="","",F6*G6) | J6: =IF(C6="","",$H6*Resumen_Socios!$D$5) | K6: =IF(C6="","",$H6*Resumen_Socios!$D$6) | L6: =IF(C6="","",IF(I6="Socio1",H6,0)) | M6: =IF(C6="","",IF(I6="Socio2",H6,0))
A7: =IF(C7="","","ID"&TEXT(ROW()-4,"0000")) | H7: =IF(C7="","",F7*G7) | J7: =IF(C7="","",$H7*Resumen_Socios!$D$5) | K7: =IF(C7="","",$H7*Resumen_Socios!$D$6) | L7: =IF(C7="","",IF(I7="Socio1",H7,0)) | M7: =IF(C7="","",IF(I7="Socio2",H7,0))
A8: =IF(C8="","","ID"&TEXT(ROW()-4,"0000")) | H8: =IF(C8="","",F8*G8) | J8: =IF(C8="","",$H8*Resumen_Socios!$D$5) | K8: =IF(C8="","",$H8*Resumen_Socios!$D$6) | L8: =IF(C8="","",IF(I8="Socio1",H8,0)) | M8: =IF(C8="","",IF(I8="Socio2",H8,0))
A9: =IF(C9="","","ID"&TEXT(ROW()-4,"0000")) | H9: =IF(C9="","",F9*G9) | J9: =IF(C9="","",$H9*Resumen_Socios!$D$5) | K9: =IF(C9="","",$H9*Resumen_Socios!$D$6) | L9: =IF(C9="","",IF(I9="Socio1",H9,0)) | M9: =IF(C9="","",IF(I9="Socio2",H9,0))
A10: =IF(C10="","","ID"&TEXT(ROW()-4,"0000")) | H10: =IF(C10="","",F10*G10) | J10: =IF(C10="","",$H10*Resumen_Socios!$D$5) | K10: =IF(C10="","",$H10*Resumen_Socios!$D$6) | L10: =IF(C10="","",IF(I10="Socio1",H10,0)) | M10: =IF(C10="","",IF(I10="Socio2",H10,0))
A11: =IF(C11="","","ID"&TEXT(ROW()-4,"0000")) | H11: =IF(C11="","",F11*G11) | J11: =IF(C11="","",$H11*Resumen_Socios!$D$5) | K11: =IF(C11="","",$H11*Resumen_Socios!$D$6) | L11: =IF(C11="","",IF(I11="Socio1",H11,0)) | M11: =IF(C11="","",IF(I11="Socio2",H11,0))
A12: =IF(C12="","","ID"&TEXT(ROW()-4,"0000")) | H12: =IF(C12="","",F12*G12) | J12: =IF(C12="","",$H12*Resumen_Socios!$D$5) | K12: =IF(C12="","",$H12*Resumen_Socios!$D$6) | L12: =IF(C12="","",IF(I12="Socio1",H12,0)) | M12: =IF(C12="","",IF(I12="Socio2",H12,0))
A13: =IF(C13="","","ID"&TEXT(ROW()-4,"0000")) | H13: =IF(C13="","",F13*G13) | J13: =IF(C13="","",$H13*Resumen_Socios!$D$5) | K13: =IF(C13="","",$H13*Resumen_Socios!$D$6) | L13: =IF(C13="","",IF(I13="Socio1",H13,0)) | M13: =IF(C13="","",IF(I13="Socio2",H13,0))
A14: =IF(C14="","","ID"&TEXT(ROW()-4,"0000")) | H14: =IF(C14="","",F14*G14) | J14: =IF(C14="","",$H14*Resumen_Socios!$D$5) | K14: =IF(C14="","",$H14*Resumen_Socios!$D$6) | L14: =IF(C14="","",IF(I14="Socio1",H14,0)) | M14: =IF(C14="","",IF(I14="Socio2",H14,0))
A15: =IF(C15="","","ID"&TEXT(ROW()-4,"0000")) | H15: =IF(C15="","",F15*G15) | J15: =IF(C15="","",$H15*Resumen_Socios!$D$5) | K15: =IF(C15="","",$H15*Resumen_Socios!$D$6) | L15: =IF(C15="","",IF(I15="Socio1",H15,0)) | M15: =IF(C15="","",IF(I15="Socio2",H15,0))
A16: =IF(C16="","","ID"&TEXT(ROW()-4,"0000")) | H16: =IF(C16="","",F16*G16) | J16: =IF(C16="","",$H16*Resumen_Socios!$D$5) | K16: =IF(C16="","",$H16*Resumen_Socios!$D$6) | L16: =IF(C16="","",IF(I16="Socio1",H16,0)) | M16: =IF(C16="","",IF(I16="Socio2",H16,0))
A17: =IF(C17="","","ID"&TEXT(ROW()-4,"0000")) | H17: =IF(C17="","",F17*G17) | J17: =IF(C17="","",$H17*Resumen_Socios!$D$5) | K17: =IF(C17="","",$H17*Resumen_Socios!$D$6) | L17: =IF(C17="","",IF(I17="Socio1",H17,0)) | M17: =IF(C17="","",IF(I17="Socio2",H17,0))
... A34: =IF(C34="","","ID"&TEXT(ROW()-4,"0000")) | H34: =IF(C34="","",F34*G34) | J34: =IF(C34="","",$H34*Resumen_Socios!$D$5) | K34: =IF(C34="","",$H34*Resumen_Socios!$D$6) | L34: =IF(C34="","",IF(I34="Socio1",H34,0)) | M34: =IF(C34="","",IF(I34="Socio2",H34,0))
C36: TOTALES | H36: =SUM(H5:H34) -> 1300000 | J36: =SUM(J5:J34) -> 845000 | K36: =SUM(K5:K34) -> 455000 | L36: =SUM(L5:L34) -> 1300000 | M36: =SUM(M5:M34) -> 0

Sheet Costos_Compras
A1: COSTOS / COMPRAS AL PROVEEDOR (detalle de mercadería)
A2: Detalle de cada factura de China. El ID_Pago vincula esta fila con la hoja Pagos_Aportes.
A4: ID | B4: Fecha | C4: Proveedor | D4: N° Factura proveedor | E4: ID_Pago (vínculo) | F4: Producto / Ítem | G4: Cantidad | H4: Precio unit. (USD) | I4: Total (USD) | J4: Comprobante factura (archivo) | K4: Estado envío | L4: Notas
A5: =IF(C5="","","C"&TEXT(ROW()-4,"0000")) -> C0001 | B5: 2026-08-27 | C5: Proveedor Yiwu Fishing Co. | D5: INV-2026-045 | E5: ID0001 | F5: Señuelo cuchara 7cm - surtido colores | G5: 500 | H5: 1.8 | I5: =G5*H5 -> 900 | J5: 2026-08-27_ID0001_factura_proveedor_pedido45.pdf | K5: En tránsito | L5: Contenedor consolidado
A6: =IF(C6="","","C"&TEXT(ROW()-4,"0000")) | I6: =IF(C6="","",G6*H6)
A7: =IF(C7="","","C"&TEXT(ROW()-4,"0000")) | I7: =IF(C7="","",G7*H7)
A8: =IF(C8="","","C"&TEXT(ROW()-4,"0000")) | I8: =IF(C8="","",G8*H8)
A9: =IF(C9="","","C"&TEXT(ROW()-4,"0000")) | I9: =IF(C9="","",G9*H9)
A10: =IF(C10="","","C"&TEXT(ROW()-4,"0000")) | I10: =IF(C10="","",G10*H10)
A11: =IF(C11="","","C"&TEXT(ROW()-4,"0000")) | I11: =IF(C11="","",G11*H11)
A12: =IF(C12="","","C"&TEXT(ROW()-4,"0000")) | I12: =IF(C12="","",G12*H12)
A13: =IF(C13="","","C"&TEXT(ROW()-4,"0000")) | I13: =IF(C13="","",G13*H13)
A14: =IF(C14="","","C"&TEXT(ROW()-4,"0000")) | I14: =IF(C14="","",G14*H14)
A15: =IF(C15="","","C"&TEXT(ROW()-4,"0000")) | I15: =IF(C15="","",G15*H15)
A16: =IF(C16="","","C"&TEXT(ROW()-4,"0000")) | I16: =IF(C16="","",G16*H16)
A17: =IF(C17="","","C"&TEXT(ROW()-4,"0000")) | I17: =IF(C17="","",G17*H17)
... A34: =IF(C34="","","C"&TEXT(ROW()-4,"0000")) | I34: =IF(C34="","",G34*H34)
F36: TOTAL USD | I36: =SUM(I5:I34) -> 900

Sheet Ventas_Ingresos
A1: VENTAS / INGRESOS
A2: Cada venta de señuelos, sea online, mayorista o local.
A4: ID | B4: Fecha | C4: Cliente / Canal | D4: Producto | E4: Cantidad | F4: Precio unit. (ARS) | G4: Total (ARS) | H4: Medio de pago | I4: Comprobante (archivo) | J4: Estado | K4: Notas
A5: =IF(C5="","","V"&TEXT(ROW()-4,"0000")) -> V0001 | B5: 2026-08-27 | C5: Pesca Total (mayorista) | D5: Señuelo cuchara 7cm | E5: 50 | F5: 3500 | G5: =E5*F5 -> 175000 | H5: Transferencia | I5: 2026-08-27_ID0001_recibo_venta.pdf | J5: Cobrado | K5: Primer pedido mayorista
A6: =IF(C6="","","V"&TEXT(ROW()-4,"0000")) | G6: =IF(C6="","",E6*F6)
A7: =IF(C7="","","V"&TEXT(ROW()-4,"0000")) | G7: =IF(C7="","",E7*F7)
A8: =IF(C8="","","V"&TEXT(ROW()-4,"0000")) | G8: =IF(C8="","",E8*F8)
A9: =IF(C9="","","V"&TEXT(ROW()-4,"0000")) | G9: =IF(C9="","",E9*F9)
A10: =IF(C10="","","V"&TEXT(ROW()-4,"0000")) | G10: =IF(C10="","",E10*F10)
A11: =IF(C11="","","V"&TEXT(ROW()-4,"0000")) | G11: =IF(C11="","",E11*F11)
A12: =IF(C12="","","V"&TEXT(ROW()-4,"0000")) | G12: =IF(C12="","",E12*F12)
A13: =IF(C13="","","V"&TEXT(ROW()-4,"0000")) | G13: =IF(C13="","",E13*F13)
A14: =IF(C14="","","V"&TEXT(ROW()-4,"0000")) | G14: =IF(C14="","",E14*F14)
A15: =IF(C15="","","V"&TEXT(ROW()-4,"0000")) | G15: =IF(C15="","",E15*F15)
A16: =IF(C16="","","V"&TEXT(ROW()-4,"0000")) | G16: =IF(C16="","",E16*F16)
A17: =IF(C17="","","V"&TEXT(ROW()-4,"0000")) | G17: =IF(C17="","",E17*F17)
... A34: =IF(C34="","","V"&TEXT(ROW()-4,"0000")) | G34: =IF(C34="","",E34*F34)
D36: TOTAL VENTAS | G36: =SUM(G5:G34) -> 175000

Sheet Resumen_Socios
B2: RESUMEN DE SOCIOS Y REPARTO
B3: Configurar acá el % de reparto (celdas amarillas). Todo lo demás se calcula solo.
B5: % Socio 1 | D5: 0.65
B6: % Socio 2 | D6: 0.35
B8: Verificación (debe sumar 100%) | D8: =D5+D6 -> 1
B11: APORTES REALIZADOS (según Pagos_Aportes)
C12: Socio 1 | D12: Socio 2 | E12: Total
B13: Le correspondía aportar (ARS) | C13: =Pagos_Aportes!J36 -> 845000 | D13: =Pagos_Aportes!K36 -> 455000 | E13: =C13+D13 -> 1300000
B14: Aportó realmente (ARS) | C14: =Pagos_Aportes!L36 -> 1300000 | D14: =Pagos_Aportes!M36 -> 0 | E14: =C14+D14 -> 1300000
B15: Saldo (aportó - correspondía) | C15: =C14-C13 -> 455000 | D15: =D14-D13 -> -455000 | E15: =C15+D15 -> 0
B17: Interpretación del saldo:
B18: Si el saldo de un socio es POSITIVO, significa que puso de más y el otro socio le debe esa diferencia (o se descuenta del próximo pago que le toque hacer).
B21: RESULTADO DEL PERÍODO Y REPARTO DE GANANCIA
B22: Total Ingresos (Ventas) | D22: =Ventas_Ingresos!G36 -> 175000
B23: Total Costos/Pagos (Pagos_Aportes) | D23: =Pagos_Aportes!H36 -> 1300000
B24: Ganancia / Pérdida neta | D24: =D22-D23 -> -1125000
B25: Corresponde a Socio 1 (según %) | D25: =D24*D5 -> -731250
B26: Corresponde a Socio 2 (según %) | D26: =D24*D6 -> -393750
